hyppo/__init__.py
hyppo/causal/__init__.py
hyppo/causal/base.py
hyppo/causal/causal_cdcorr.py
hyppo/causal/cleaners.py
hyppo/causal/propensity_model.py
hyppo/causal/tests/__init__.py
hyppo/causal/tests/test_causal_cdcorr.py
hyppo/causal/tests/test_propensity_model.py
hyppo/conditional/FCIT.py
hyppo/conditional/__init__.py
hyppo/conditional/_utils.py
hyppo/conditional/base.py
hyppo/conditional/cdcorr.py
hyppo/conditional/kci.py
hyppo/conditional/pcorr.py
hyppo/conditional/pdcorr.py
hyppo/conditional/tests/__init__.py
hyppo/conditional/tests/test_FCIT.py
hyppo/conditional/tests/test_cdcorr.py
hyppo/conditional/tests/test_kci.py
hyppo/conditional/tests/test_pcorr.py
hyppo/conditional/tests/test_pdcorr.py
hyppo/conditional/tests/test_utils.py
hyppo/d_variate/__init__.py
hyppo/d_variate/_utils.py
hyppo/d_variate/base.py
hyppo/d_variate/dhsic.py
hyppo/d_variate/tests/__init__.py
hyppo/d_variate/tests/test_dhsic.py
hyppo/discrim/__init__.py
hyppo/discrim/_utils.py
hyppo/discrim/base.py
hyppo/discrim/discrim_one_samp.py
hyppo/discrim/discrim_two_samp.py
hyppo/discrim/tests/__init__.py
hyppo/discrim/tests/test_discrim_one_samp.py
hyppo/discrim/tests/test_discrim_two_samp.py
hyppo/discrim/tests/test_utils.py
hyppo/independence/__init__.py
hyppo/independence/_utils.py
hyppo/independence/base.py
hyppo/independence/cca.py
hyppo/independence/dcorr.py
hyppo/independence/hhg.py
hyppo/independence/hsic.py
hyppo/independence/kmerf.py
hyppo/independence/max_margin.py
hyppo/independence/mgc.py
hyppo/independence/rv.py
hyppo/independence/tests/__init__.py
hyppo/independence/tests/test_cca.py
hyppo/independence/tests/test_dcorr.py
hyppo/independence/tests/test_hhg.py
hyppo/independence/tests/test_hhgfast.py
hyppo/independence/tests/test_hsic.py
hyppo/independence/tests/test_kmerf.py
hyppo/independence/tests/test_maxmargin.py
hyppo/independence/tests/test_mgc.py
hyppo/independence/tests/test_rvcorr.py
hyppo/independence/tests/test_utils.py
hyppo/kgof/__init__.py
hyppo/kgof/_utils.py
hyppo-0.5.2.dist-info/licenses/LICENSE.md
hyppo-0.5.2.dist-info/METADATA
hyppo-0.5.2.dist-info/WHEEL
hyppo-0.5.2.dist-info/top_level.txt
hyppo-0.5.2.dist-info/RECORD
