Metadata-Version: 2.4
Name: hyppo
Version: 0.5.2
Summary: A comprehensive independence testing package
Home-page: https://github.com/neurodata/hyppo
Author: ('Sambit Panda',)
Author-email: spanda3@jhu.edu
License: MIT License
Classifier: Development Status :: 3 - Alpha
Classifier: Intended Audience :: Science/Research
Classifier: Topic :: Scientific/Engineering :: Mathematics
Classifier: License :: OSI Approved :: MIT License
Classifier: Programming Language :: Python :: 3
Classifier: Programming Language :: Python :: 3.8
Classifier: Programming Language :: Python :: 3.9
Classifier: Programming Language :: Python :: 3.10
Classifier: Programming Language :: Python :: 3.11
Classifier: Programming Language :: Python :: 3.12
Classifier: Programming Language :: Python :: 3.13
Classifier: Programming Language :: Python :: 3.14
License-File: LICENSE.md
Requires-Dist: numpy>=1.17
Requires-Dist: scipy>=1.4.0
Requires-Dist: numba>=0.46
Requires-Dist: scikit-learn>=0.19.1
Requires-Dist: autograd>=1.3
Requires-Dist: statsmodels>=0.14.1
Requires-Dist: patsy>=0.5.1
Requires-Dist: pandas>=2.2.3
Requires-Dist: future>=1.0.0
Dynamic: author
Dynamic: author-email
Dynamic: classifier
Dynamic: description
Dynamic: description-content-type
Dynamic: home-page
Dynamic: license
Dynamic: license-file
Dynamic: requires-dist
Dynamic: summary
